alissonSomav2/__init__.py
alissonSomav2/somav2.py
alissonSomav2-0.1.dist-info/LICENSE
alissonSomav2-0.1.dist-info/METADATA
alissonSomav2-0.1.dist-info/WHEEL
alissonSomav2-0.1.dist-info/top_level.txt
alissonSomav2-0.1.dist-info/RECORD
